PyNetPing/__init__.py
PyNetPing/__main__.py
PyNetPing/async_engine.py
PyNetPing/cli.py
PyNetPing/dns.py
PyNetPing/http.py
PyNetPing/icmp4.py
PyNetPing/icmp6.py
PyNetPing/output.py
PyNetPing/ping.py
PyNetPing/rate.py
PyNetPing/result.py
PyNetPing/stats.py
PyNetPing/tcp.py
PyNetPing/utils.py
pynetping-1.0.1.dist-info/licenses/LICENSE.md
pynetping-1.0.1.dist-info/METADATA
pynetping-1.0.1.dist-info/WHEEL
pynetping-1.0.1.dist-info/entry_points.txt
pynetping-1.0.1.dist-info/top_level.txt
pynetping-1.0.1.dist-info/RECORD
