Metadata-Version: 2.4
Name: pynetping
Version: 1.0.1
Summary: Python ping library and CLI tool with ICMP, TCP, HTTP, and DNS fallback
Author: Sreeraj S Kurup
License: MIT License
Keywords: ping,network,icmp,tcp,http,dns,cli
Classifier: Programming Language :: Python :: 3
Classifier: Operating System :: OS Independent
Classifier: License :: OSI Approved :: MIT License
Requires-Python: >=3.10
License-File: LICENSE.md
Dynamic: license-file
